MANIFEST.in
README.rst
csg_dicoms_anonymizer.spec
setup.py
csg_dicoms_anonymizer/__init__.py
csg_dicoms_anonymizer/__main__.py
csg_dicoms_anonymizer/_version.py
csg_dicoms_anonymizer/csg_dicoms_anonymizer.py
csg_dicoms_anonymizer.egg-info/PKG-INFO
csg_dicoms_anonymizer.egg-info/SOURCES.txt
csg_dicoms_anonymizer.egg-info/dependency_links.txt
csg_dicoms_anonymizer.egg-info/entry_points.txt
csg_dicoms_anonymizer.egg-info/top_level.txt
csg_dicoms_anonymizer/csg_fileutil_libs/__init__.py
csg_dicoms_anonymizer/csg_fileutil_libs/argparse.py
csg_dicoms_anonymizer/csg_fileutil_libs/aux_funcs.py
csg_dicoms_anonymizer/csg_fileutil_libs/tee.py
csg_dicoms_anonymizer/csg_fileutil_libs/dateutil/__init__.py
csg_dicoms_anonymizer/csg_fileutil_libs/dateutil/_common.py
csg_dicoms_anonymizer/csg_fileutil_libs/dateutil/easter.py
csg_dicoms_anonymizer/csg_fileutil_libs/dateutil/parser.py
csg_dicoms_anonymizer/csg_fileutil_libs/dateutil/relativedelta.py
csg_dicoms_anonymizer/csg_fileutil_libs/dateutil/rrule.py
csg_dicoms_anonymizer/csg_fileutil_libs/dateutil/tzwin.py
csg_dicoms_anonymizer/csg_fileutil_libs/dateutil/test/__init__.py
csg_dicoms_anonymizer/csg_fileutil_libs/dateutil/test/_common.py
csg_dicoms_anonymizer/csg_fileutil_libs/dateutil/test/test_easter.py
csg_dicoms_anonymizer/csg_fileutil_libs/dateutil/test/test_imports.py
csg_dicoms_anonymizer/csg_fileutil_libs/dateutil/test/test_parser.py
csg_dicoms_anonymizer/csg_fileutil_libs/dateutil/test/test_relativedelta.py
csg_dicoms_anonymizer/csg_fileutil_libs/dateutil/test/test_rrule.py
csg_dicoms_anonymizer/csg_fileutil_libs/dateutil/test/test_tz.py
csg_dicoms_anonymizer/csg_fileutil_libs/dateutil/tz/__init__.py
csg_dicoms_anonymizer/csg_fileutil_libs/dateutil/tz/_common.py
csg_dicoms_anonymizer/csg_fileutil_libs/dateutil/tz/tz.py
csg_dicoms_anonymizer/csg_fileutil_libs/dateutil/tz/win.py
csg_dicoms_anonymizer/csg_fileutil_libs/dateutil/zoneinfo/__init__.py
csg_dicoms_anonymizer/csg_fileutil_libs/dateutil/zoneinfo/dateutil-zoneinfo.tar.gz
csg_dicoms_anonymizer/csg_fileutil_libs/dateutil/zoneinfo/rebuild.py
csg_dicoms_anonymizer/csg_fileutil_libs/distance/README.md
csg_dicoms_anonymizer/csg_fileutil_libs/distance/__init__.py
